{
  "VWAP_RSI_5M": {
    "sl_mult": 1.0,
    "tp_mult": 1.0,
    "conf_floor": 0.6,
    "enabled": true,
    "trades_seen": 6,
    "wins": 2,
    "win_rate": 0.333,
    "last_adapted": null,
    "adapt_count": 0
  },
  "ORB_5M": {
    "sl_mult": 1.0,
    "tp_mult": 1.0,
    "conf_floor": 0.6,
    "enabled": true,
    "trades_seen": 0,
    "wins": 0,
    "win_rate": null,
    "last_adapted": null,
    "adapt_count": 0
  },
  "TREND_MOM_5M": {
    "sl_mult": 1.5,
    "tp_mult": 0.75,
    "conf_floor": 0.8,
    "enabled": true,
    "trades_seen": 11,
    "wins": 3,
    "win_rate": 0.273,
    "last_adapted": "2026-04-29T06:47:43.532874+00:00",
    "adapt_count": 10
  },
  "EMA_PB_15M": {
    "sl_mult": 1.0,
    "tp_mult": 1.0,
    "conf_floor": 0.6,
    "enabled": true,
    "trades_seen": 0,
    "wins": 0,
    "win_rate": null,
    "last_adapted": null,
    "adapt_count": 0
  },
  "SQUEEZE_15M": {
    "sl_mult": 1.0,
    "tp_mult": 1.0,
    "conf_floor": 0.6,
    "enabled": true,
    "trades_seen": 0,
    "wins": 0,
    "win_rate": null,
    "last_adapted": null,
    "adapt_count": 0
  },
  "ABSORB_15M": {
    "sl_mult": 1.0,
    "tp_mult": 1.0,
    "conf_floor": 0.6,
    "enabled": true,
    "trades_seen": 0,
    "wins": 0,
    "win_rate": null,
    "last_adapted": null,
    "adapt_count": 0
  },
  "PDH_PDL_SWEEP_5M": {
    "sl_mult": 1.0,
    "tp_mult": 1.0,
    "conf_floor": 0.6,
    "enabled": true,
    "trades_seen": 3,
    "wins": 1,
    "win_rate": 0.333,
    "last_adapted": null,
    "adapt_count": 0
  },
  "CAMARILLA_5M": {
    "sl_mult": 1.5,
    "tp_mult": 0.75,
    "conf_floor": 0.8,
    "enabled": true,
    "trades_seen": 20,
    "wins": 9,
    "win_rate": 0.45,
    "last_adapted": "2026-04-29T20:00:17.882505+00:00",
    "adapt_count": 15
  },
  "NR7_BREAKOUT_5M": {
    "sl_mult": 1.0,
    "tp_mult": 1.0,
    "conf_floor": 0.6,
    "enabled": true,
    "trades_seen": 7,
    "wins": 3,
    "win_rate": 0.429,
    "last_adapted": null,
    "adapt_count": 0
  },
  "MSS_FOREX_15M": {
    "sl_mult": 1.0,
    "tp_mult": 1.0,
    "conf_floor": 0.6,
    "enabled": true,
    "trades_seen": 10,
    "wins": 4,
    "win_rate": 0.4,
    "last_adapted": "2026-04-29T20:47:30.150656+00:00",
    "adapt_count": 1
  },
  "BB_SCALP_5M": {
    "sl_mult": 1.0,
    "tp_mult": 1.0,
    "conf_floor": 0.6,
    "enabled": true,
    "trades_seen": 0,
    "wins": 0,
    "win_rate": null,
    "last_adapted": null,
    "adapt_count": 0
  },
  "STOCH_CROSS_5M": {
    "sl_mult": 1.0,
    "tp_mult": 1.0,
    "conf_floor": 0.6,
    "enabled": true,
    "trades_seen": 1,
    "wins": 0,
    "win_rate": 0.0,
    "last_adapted": null,
    "adapt_count": 0
  },
  "EMA_MICRO_CROSS_5M": {
    "sl_mult": 1.0,
    "tp_mult": 1.0,
    "conf_floor": 0.6,
    "enabled": true,
    "trades_seen": 3,
    "wins": 2,
    "win_rate": 0.667,
    "last_adapted": null,
    "adapt_count": 0
  },
  "DOUBLE_BOT_BREAKOUT_5M": {
    "sl_mult": 1.0,
    "tp_mult": 1.0,
    "conf_floor": 0.6,
    "enabled": false,
    "trades_seen": 0,
    "wins": 0,
    "win_rate": null,
    "last_adapted": null,
    "adapt_count": 0
  },
  "HS_BREAKDOWN_5M": {
    "sl_mult": 1.0,
    "tp_mult": 1.0,
    "conf_floor": 0.6,
    "enabled": false,
    "trades_seen": 0,
    "wins": 0,
    "win_rate": null,
    "last_adapted": null,
    "adapt_count": 0
  },
  "FLAG_BREAKOUT_5M": {
    "sl_mult": 1.0,
    "tp_mult": 1.0,
    "conf_floor": 0.6,
    "enabled": false,
    "trades_seen": 0,
    "wins": 0,
    "win_rate": null,
    "last_adapted": null,
    "adapt_count": 0
  }
}